mozapkpublisher/__init__.py
mozapkpublisher/check_apks.py
mozapkpublisher/check_rollout.py
mozapkpublisher/get_sgs_token.py
mozapkpublisher/push_aab.py
mozapkpublisher/push_apk.py
mozapkpublisher/common/__init__.py
mozapkpublisher/common/exceptions.py
mozapkpublisher/common/main_logging.py
mozapkpublisher/common/store.py
mozapkpublisher/common/utils.py
mozapkpublisher/common/aab/__init__.py
mozapkpublisher/common/aab/extractor.py
mozapkpublisher/common/apk/__init__.py
mozapkpublisher/common/apk/checker.py
mozapkpublisher/common/apk/extractor.py
mozapkpublisher/common/apk/history.py
mozapkpublisher/sgs_api/__init__.py
mozapkpublisher/sgs_api/auth.py
mozapkpublisher/sgs_api/content_info.py
mozapkpublisher/sgs_api/error.py
mozapkpublisher/sgs_api/utils.py
mozapkpublisher/test/__init__.py
mozapkpublisher/test/test_check_rollout.py
mozapkpublisher/test/test_push_aab.py
mozapkpublisher/test/test_push_apk.py
mozapkpublisher/test/common/__init__.py
mozapkpublisher/test/common/test_store.py
mozapkpublisher/test/common/test_utils.py
mozapkpublisher/test/common/aab/__init__.py
mozapkpublisher/test/common/aab/test_init.py
mozapkpublisher/test/common/apk/__init__.py
mozapkpublisher/test/common/apk/test_checker.py
mozapkpublisher/test/common/apk/test_extractor.py
mozapkpublisher/test/common/apk/test_history.py
mozapkpublisher/test/common/apk/test_init.py
mozapkpublisher/test/data/SHA512SUMS
mozapkpublisher/test/data/blob
mozapkpublisher/test/data/checksums.broken
mozapkpublisher/test/data/checksums.old
mozapkpublisher/test/data/checksums.tc
mozapkpublisher/test/integration/__init__.py
mozapkpublisher/test/integration/test_check_apks.py
mozapkpublisher/test/integration/test_upload_sgs.py
mozapkpublisher/test/sgs/__init__.py
mozapkpublisher/test/sgs/common.py
mozapkpublisher/test/sgs/fixtures.py
mozapkpublisher/test/sgs/test_auth.py
mozapkpublisher/test/sgs/test_content_info.py
mozapkpublisher/test/sgs/test_dry_run.py
mozapkpublisher/test/sgs/test_rollout.py
mozapkpublisher-11.0.0.dist-info/METADATA
mozapkpublisher-11.0.0.dist-info/WHEEL
mozapkpublisher-11.0.0.dist-info/licenses/LICENSE
mozapkpublisher-11.0.0.dist-info/RECORD
