Metadata-Version: 2.4
Name: mozapkpublisher
Version: 11.0.0
Summary: Scripts to get and push Firefox for Android to Google Play Store
Author-email: Mozilla Release Engineering <release+python@mozilla.com>
License-Expression: MPL-2.0
License-File: LICENSE
Classifier: Programming Language :: Python :: 3.11
Classifier: Programming Language :: Python :: 3.12
Classifier: Programming Language :: Python :: 3.13
Requires-Python: >=3.11
Requires-Dist: aiohttp
Requires-Dist: google-api-python-client
Requires-Dist: google-auth
Requires-Dist: mozilla-version
Requires-Dist: pyaxmlparser
Requires-Dist: pyjwt
Requires-Dist: requests
